qlookz/__init__.py
qlookz/cache.py
qlookz/cli.py
qlookz-0.1.0.dist-info/METADATA
qlookz-0.1.0.dist-info/WHEEL
qlookz-0.1.0.dist-info/entry_points.txt
qlookz-0.1.0.dist-info/licenses/LICENSE
qlookz-0.1.0.dist-info/RECORD
