Metadata-Version: 2.4
Name: qlookz
Version: 0.1.0
Summary: Quick Look Zsh - Cache command outputs for instant retrieval
Project-URL: Homepage, https://github.com/qlookz/qlookz
Project-URL: Repository, https://github.com/qlookz/qlookz
Author: qlookz contributors
License-Expression: MIT
License-File: LICENSE
Keywords: bash,cache,cli,productivity,shell,zsh
Classifier: Development Status :: 4 - Beta
Classifier: Environment :: Console
Classifier: Intended Audience :: Developers
Classifier: License :: OSI Approved :: MIT License
Classifier: Operating System :: OS Independent
Classifier: Programming Language :: Python :: 3
Classifier: Programming Language :: Python :: 3.8
Classifier: Programming Language :: Python :: 3.9
Classifier: Programming Language :: Python :: 3.10
Classifier: Programming Language :: Python :: 3.11
Classifier: Programming Language :: Python :: 3.12
Classifier: Topic :: System :: Shells
Classifier: Topic :: Utilities
Requires-Python: >=3.8
